bk-itsm-sdk/__init__.py
bk-itsm-sdk/exceptions.py
bk-itsm-sdk/itsm.py
bk-itsm-sdk/tests.py
bk-itsm-sdk/api/__init__.py
bk-itsm-sdk/api/client.py
bk-itsm-sdk/api/http.py
itsm_sdk/__init__.py
itsm_sdk/exceptions.py
itsm_sdk/itsm.py
itsm_sdk/tests.py
itsm_sdk/api/__init__.py
itsm_sdk/api/client.py
itsm_sdk/api/http.py
bk_itsm_sdk-1.0.2.dist-info/LICENSE
bk_itsm_sdk-1.0.2.dist-info/METADATA
bk_itsm_sdk-1.0.2.dist-info/WHEEL
bk_itsm_sdk-1.0.2.dist-info/top_level.txt
bk_itsm_sdk-1.0.2.dist-info/RECORD
