Metadata-Version: 2.1
Name: bk-itsm-sdk
Version: 1.0.2
Summary: A Itsm-SDK package
Home-page: https://bk.tencent.com/docs/
Author: secloud
Author-email: 869820505@qq.com
License: MIT License
Platform: all
Classifier: Intended Audience :: Developers
Classifier: Operating System :: OS Independent
Classifier: Natural Language :: Chinese (Simplified)
Classifier: Programming Language :: Python
Classifier: Programming Language :: Python :: 2
Classifier: Programming Language :: Python :: 2.7
Classifier: Programming Language :: Python :: 3
Classifier: Programming Language :: Python :: 3.5
Classifier: Programming Language :: Python :: 3.6
Classifier: Programming Language :: Python :: 3.7
Classifier: Programming Language :: Python :: 3.8
Classifier: Topic :: Software Development :: Libraries
License-File: LICENSE
Requires-Dist: certifi (==2022.6.15)
Requires-Dist: requests (==2.27.1)
Requires-Dist: curlify (==2.2.1)
